gaganpdf/__init__.py
gaganpdf/pdf2img.py
gaganpdf/pdf2text.py
gagandeep1pdf-1.0.dist-info/LICENSE
gagandeep1pdf-1.0.dist-info/METADATA
gagandeep1pdf-1.0.dist-info/WHEEL
gagandeep1pdf-1.0.dist-info/top_level.txt
gagandeep1pdf-1.0.dist-info/RECORD
