Metadata-Version: 2.1
Name: gagandeep1pdf
Version: 1.0
Summary: My homepage
Home-page: UNKNOWN
Author: UNKNOWN
Author-email: UNKNOWN
License: UNKNOWN
Platform: UNKNOWN
